trx/__init__.py
trx/azav.py
trx/cell.py
trx/center.py
trx/dataReduction.py
trx/filters.py
trx/id9.py
trx/mask.py
trx/peaks.py
trx/utils_old.py
trx/utils/__init__.py
trx/utils/absorption.py
trx/utils/files.py
trx/utils/misc.py
trx/utils/numeric.py
trx/utils/plot.py
trx/utils/scattering.py
trx/utils/spec.py
trx/utils/string.py
trx-0.6.5.dist-info/LICENSE
trx-0.6.5.dist-info/METADATA
trx-0.6.5.dist-info/WHEEL
trx-0.6.5.dist-info/top_level.txt
trx-0.6.5.dist-info/RECORD
