Metadata-Version: 2.1
Name: trx
Version: 0.6.5
Summary: tools for (T)ime (R)esolved (X)-ray techniques
Home-page: https://github.com/marcocamma/trx
Author: marco cammarata
Author-email: marcocamma@gmail.com
License: MIT
Platform: UNKNOWN
Requires-Dist: datastorage (>=0.4.3)
Requires-Dist: fabio
Requires-Dist: matplotlib
Requires-Dist: numpy
Requires-Dist: pyFAI
Requires-Dist: statsmodels
